{
  "_comment": "State dependent exemption/credit levers for the dashboard. mechanism=baseline sets a scalar per-dependent param directly (amount editable; 0 = eliminate). mechanism=contrib flips a contributed in_effect flag and sets its amount (RI/DE/OR/VA — separates the dependent portion of a bundled personal exemption). mechanism=repeal flips the broad gov.contrib.repeal_state_dependent_exemptions.in_effect flag (eliminate-only; for bundled/bracketed states with no clean scalar). current_amount is the latest per-dependent value (display + no-op default). kind labels the lever (exemption/credit/deduction). States absent here have no dashboard lever (no income tax, no dependent exemption, or a bundled exemption with no PE-US separation yet).",

  "CA": { "mechanism": "baseline", "amount_path": "gov.states.ca.tax.income.exemptions.dependent_amount", "current_amount": 486, "amount_editable": true, "kind": "exemption" },
  "GA": { "mechanism": "baseline", "amount_path": "gov.states.ga.tax.income.exemptions.dependent", "current_amount": 5000, "amount_editable": true, "kind": "exemption" },
  "IA": { "mechanism": "baseline", "amount_path": "gov.states.ia.tax.income.credits.exemption.dependent", "current_amount": 40, "amount_editable": true, "kind": "credit" },
  "IL": { "mechanism": "baseline", "amount_path": "gov.states.il.tax.income.exemption.dependent", "current_amount": 2925, "amount_editable": true, "kind": "exemption" },
  "IN": { "mechanism": "baseline", "amount_path": "gov.states.in.tax.income.exemptions.additional.amount", "current_amount": 1500, "amount_editable": true, "kind": "exemption", "note": "Indiana's additional exemption per qualifying child ($1,500). The base $1,000 per-person exemption that also covers dependents is bundled and would need a contributed reform to separate." },
  "KS": { "mechanism": "baseline", "amount_path": "gov.states.ks.tax.income.exemptions.by_filing_status.dependent", "current_amount": 2320, "amount_editable": true, "kind": "exemption" },
  "MA": { "mechanism": "baseline", "amount_path": "gov.states.ma.tax.income.exemptions.dependent", "current_amount": 1000, "amount_editable": true, "kind": "exemption" },
  "MS": { "mechanism": "baseline", "amount_path": "gov.states.ms.tax.income.exemptions.dependents.amount", "current_amount": 1500, "amount_editable": true, "kind": "exemption" },
  "NJ": { "mechanism": "baseline", "amount_path": "gov.states.nj.tax.income.exemptions.dependents.amount", "current_amount": 1500, "amount_editable": true, "kind": "exemption", "extra_params": [{ "name": "college_amount", "label": "Additional per college dependent (under 22)", "path": "gov.states.nj.tax.income.exemptions.dependents_attending_college.amount", "current_amount": 1000 }] },
  "NY": { "mechanism": "baseline", "amount_path": "gov.states.ny.tax.income.exemptions.dependent", "current_amount": 1000, "amount_editable": true, "kind": "exemption" },

  "RI": { "mechanism": "contrib", "in_effect": "gov.contrib.states.ri.dependent_exemption.in_effect", "amount": "gov.contrib.states.ri.dependent_exemption.amount", "current_amount": 5200, "amount_editable": true, "kind": "exemption" },
  "DE": { "mechanism": "contrib", "in_effect": "gov.contrib.states.de.dependent_credit.in_effect", "amount": "gov.contrib.states.de.dependent_credit.amount", "current_amount": 110, "amount_editable": true, "kind": "credit" },
  "OR": { "mechanism": "contrib", "in_effect": "gov.contrib.states.or.dependent_exemption_credit.in_effect", "amount": "gov.contrib.states.or.dependent_exemption_credit.amount", "current_amount": 256, "amount_editable": true, "kind": "credit" },
  "VA": { "mechanism": "contrib", "in_effect": "gov.contrib.states.va.dependent_exemption.in_effect", "amount": "gov.contrib.states.va.dependent_exemption.amount", "current_amount": 930, "amount_editable": true, "kind": "exemption" },

  "HI": { "mechanism": "contrib", "in_effect": "gov.contrib.states.hi.dependent_exemption.in_effect", "amount": "gov.contrib.states.hi.dependent_exemption.amount", "current_amount": 1144, "amount_editable": true, "kind": "exemption", "note": "Dependent portion of the state's personal exemption, separated by the contributed reform (us#8696)." },
  "MD": {"mechanism": "baseline", "amount_path": ["gov.states.md.tax.income.exemptions.personal.single[0].amount", "gov.states.md.tax.income.exemptions.personal.joint[0].amount", "gov.states.md.tax.income.exemptions.personal.head[0].amount", "gov.states.md.tax.income.exemptions.personal.separate[0].amount", "gov.states.md.tax.income.exemptions.personal.surviving_spouse[0].amount"], "amount_label": "Per person (lowest AGI tier)", "current_amount": 3200, "amount_editable": true, "kind": "exemption", "extra_params": [{"name": "amount_mid", "label": "Per person (middle AGI tier)", "path": ["gov.states.md.tax.income.exemptions.personal.single[1].amount", "gov.states.md.tax.income.exemptions.personal.joint[1].amount", "gov.states.md.tax.income.exemptions.personal.head[1].amount", "gov.states.md.tax.income.exemptions.personal.separate[1].amount", "gov.states.md.tax.income.exemptions.personal.surviving_spouse[1].amount"], "current_amount": 1600}, {"name": "amount_low", "label": "Per person (upper AGI tier)", "path": ["gov.states.md.tax.income.exemptions.personal.single[2].amount", "gov.states.md.tax.income.exemptions.personal.joint[2].amount", "gov.states.md.tax.income.exemptions.personal.head[2].amount", "gov.states.md.tax.income.exemptions.personal.separate[2].amount", "gov.states.md.tax.income.exemptions.personal.surviving_spouse[2].amount"], "current_amount": 800}, {"name": "threshold_mid_single", "label": "Middle-tier AGI cutoff \u2014 single / married-separate", "path": ["gov.states.md.tax.income.exemptions.personal.single[1].threshold", "gov.states.md.tax.income.exemptions.personal.separate[1].threshold"], "current_amount": 100000, "step": 5000, "max": 500000, "is_threshold": true}, {"name": "threshold_mid_joint", "label": "Middle-tier AGI cutoff \u2014 joint / head / surviving spouse", "path": ["gov.states.md.tax.income.exemptions.personal.joint[1].threshold", "gov.states.md.tax.income.exemptions.personal.head[1].threshold", "gov.states.md.tax.income.exemptions.personal.surviving_spouse[1].threshold"], "current_amount": 150000, "step": 5000, "max": 500000, "is_threshold": true}, {"name": "threshold_top_single", "label": "Upper-tier AGI cutoff \u2014 single / married-separate", "path": ["gov.states.md.tax.income.exemptions.personal.single[2].threshold", "gov.states.md.tax.income.exemptions.personal.separate[2].threshold"], "current_amount": 125000, "step": 5000, "max": 500000, "is_threshold": true}, {"name": "threshold_top_joint", "label": "Upper-tier AGI cutoff \u2014 joint / head / surviving spouse", "path": ["gov.states.md.tax.income.exemptions.personal.joint[2].threshold", "gov.states.md.tax.income.exemptions.personal.head[2].threshold", "gov.states.md.tax.income.exemptions.personal.surviving_spouse[2].threshold"], "current_amount": 175000, "step": 5000, "max": 500000, "is_threshold": true}], "note": "Maryland applies this exemption per person (taxpayer, spouse, and each dependent), stepped by AGI; editing it adjusts the full per-exemption schedule, not dependents alone. The per-person amounts are shared across filing statuses; the AGI cutoffs differ by filing status (single/separate vs joint/head/surviving-spouse), so each is editable separately."},
  "MI": { "mechanism": "contrib", "in_effect": "gov.contrib.states.mi.dependent_exemption.in_effect", "amount": "gov.contrib.states.mi.dependent_exemption.amount", "current_amount": 4400, "amount_editable": true, "kind": "exemption", "note": "Dependent portion of the state's personal exemption, separated by the contributed reform (us#8696)." },
  "NE": { "mechanism": "contrib", "in_effect": "gov.contrib.states.ne.dependent_exemption.in_effect", "amount": "gov.contrib.states.ne.dependent_exemption.amount", "current_amount": 157, "amount_editable": true, "kind": "credit", "note": "Dependent portion of NE's personal-exemption credit, separated by the contributed reform (us#8696)." },
  "OH": {"mechanism": "baseline", "amount_path": "gov.states.oh.tax.income.exemptions.personal.amount[0].amount", "amount_label": "Per person (MAGI under $40k)", "current_amount": 2400, "amount_editable": true, "kind": "exemption", "extra_params": [{"name": "amount_mid", "label": "Per person (MAGI $40k-$80k)", "path": "gov.states.oh.tax.income.exemptions.personal.amount[1].amount", "current_amount": 2150}, {"name": "amount_high", "label": "Per person (MAGI over $80k)", "path": "gov.states.oh.tax.income.exemptions.personal.amount[2].amount", "current_amount": 1900}, {"name": "threshold_mid", "label": "MAGI where the middle tier starts", "path": "gov.states.oh.tax.income.exemptions.personal.amount[1].threshold", "current_amount": 40001, "step": 5000, "max": 500000, "is_threshold": true}, {"name": "threshold_high", "label": "MAGI where the top tier starts", "path": "gov.states.oh.tax.income.exemptions.personal.amount[2].threshold", "current_amount": 80001, "step": 5000, "max": 500000, "is_threshold": true}], "note": "Ohio applies this exemption per person (taxpayer, spouse, and each dependent), stepped by MAGI; editing it adjusts the full per-exemption schedule, not dependents alone."},
  "OK": { "mechanism": "contrib", "in_effect": "gov.contrib.states.ok.dependent_exemption.in_effect", "amount": "gov.contrib.states.ok.dependent_exemption.amount", "current_amount": 1000, "amount_editable": true, "kind": "exemption", "note": "Dependent portion of the state's personal exemption, separated by the contributed reform (us#8696)." },
  "VT": { "mechanism": "contrib", "in_effect": "gov.contrib.states.vt.dependent_exemption.in_effect", "amount": "gov.contrib.states.vt.dependent_exemption.amount", "current_amount": 5300, "amount_editable": true, "kind": "exemption", "note": "Dependent portion of the state's personal exemption, separated by the contributed reform (us#8696)." },
  "WI": { "mechanism": "contrib", "in_effect": "gov.contrib.states.wi.dependent_exemption.in_effect", "amount": "gov.contrib.states.wi.dependent_exemption.amount", "current_amount": 700, "amount_editable": true, "kind": "exemption", "note": "Dependent portion of the state's personal exemption, separated by the contributed reform (us#8696)." },
  "WV": { "mechanism": "contrib", "in_effect": "gov.contrib.states.wv.dependent_exemption.in_effect", "amount": "gov.contrib.states.wv.dependent_exemption.amount", "current_amount": 2000, "amount_editable": true, "kind": "exemption", "note": "Dependent portion of the state's personal exemption, separated by the contributed reform (us#8696)." },

  "AL": {"mechanism": "baseline", "amount_path": "gov.states.al.tax.income.exemptions.dependent[0].amount", "amount_label": "Amount per dependent (AGI under $50k)", "current_amount": 1000, "amount_editable": true, "kind": "exemption", "extra_params": [{"name": "amount_mid", "label": "Amount per dependent (AGI $50k-$100k)", "path": "gov.states.al.tax.income.exemptions.dependent[1].amount", "current_amount": 500}, {"name": "amount_high", "label": "Amount per dependent (AGI over $100k)", "path": "gov.states.al.tax.income.exemptions.dependent[2].amount", "current_amount": 300}, {"name": "threshold_mid", "label": "AGI where the middle tier starts", "path": "gov.states.al.tax.income.exemptions.dependent[1].threshold", "current_amount": 50000, "step": 5000, "max": 500000, "is_threshold": true}, {"name": "threshold_high", "label": "AGI where the top tier starts", "path": "gov.states.al.tax.income.exemptions.dependent[2].threshold", "current_amount": 100000, "step": 5000, "max": 500000, "is_threshold": true}], "note": "Per-dependent exemption steps down by AGI ($1,000 / $500 / $300); each tier amount and the AGI cutoffs are editable."},
  "AZ": {"mechanism": "baseline", "amount_path": "gov.states.az.tax.income.credits.dependent_credit.amount[0].amount", "amount_label": "Credit per dependent (under 17)", "current_amount": 125, "amount_editable": true, "kind": "credit", "extra_params": [{"name": "amount_older", "label": "Credit per dependent (17 and older)", "path": "gov.states.az.tax.income.credits.dependent_credit.amount[1].amount", "current_amount": 25}, {"name": "threshold_age", "label": "Age the older-dependent credit starts at", "path": "gov.states.az.tax.income.credits.dependent_credit.amount[1].threshold", "current_amount": 17, "unit": "years", "step": 1, "max": 24, "is_threshold": true}], "note": "Dependent tax credit: $125/child under 17, $25 per older dependent (2026). Amounts and the age cutoff are editable."},
  "AR": { "mechanism": "contrib", "in_effect": "gov.contrib.states.ar.dependent_credit.in_effect", "amount": "gov.contrib.states.ar.dependent_credit.amount", "current_amount": 29, "amount_editable": true, "kind": "credit", "note": "Dependent slice of AR's personal tax credit ($29/dependent), separated by the contributed reform (us#8696) so it can be edited or eliminated." },
  "MN": { "mechanism": "baseline", "amount_path": "gov.states.mn.tax.income.exemptions.amount", "current_amount": 5300, "amount_editable": true, "kind": "exemption", "note": "Per-dependent exemption ($5,300), phased out with AGI." },
  "NC": { "mechanism": "repeal", "repeal_flag": "gov.contrib.repeal_state_dependent_exemptions.in_effect", "amount_editable": false, "kind": "deduction", "note": "Child deduction varies by AGI bracket and filing status (no single per-child amount), so eliminate-only." },
  "SC": { "mechanism": "baseline", "amount_path": "gov.states.sc.tax.income.deductions.dependent_exemption.amount", "current_amount": 5040, "amount_editable": true, "kind": "exemption", "note": "Per-dependent dependent exemption (§12-6-1140). Now its own parameter in policyengine-us 1.740.0 — separate from the young-child deduction (§12-6-1160), which reads its own param — so it can be edited or set to 0 to eliminate without touching the young-child deduction." },
  "UT": { "mechanism": "repeal", "repeal_flag": "gov.contrib.repeal_state_dependent_exemptions.in_effect", "amount_editable": false, "kind": "exemption", "note": "The per-dependent exemption inside the Utah Taxpayer Tax Credit shares its amount with the personal exemption, so only full repeal (which isolates ut_personal_exemption) is offered; editing the amount would need a contributed reform." }
}
